pyfread/__init__.py
pyfread/common.py
pyfread/shell.py
pyfread/cpp/__init__.py
pyfread/cpp/atom2coord.py
pyfread/loops/__init__.py
pyfread/loops/ccd.py
pyfread/loops/esst.py
pyfread/loops/fread.py
pyfread/loops/freaddb.py
pyfread/loops/loopmodel.py
pyfread/loops/multifread.py
pyfread/util/__init__.py
pyfread/util/ali.py
pyfread/util/gaps.py
pyfread/util/geohash.py
pyfread/util/getpdb.py
pyfread/util/pdb.py
pyfread/util/pdb3d.py
pyfread/util/protein.py
pyfread/util/residue.py
pyfread/util/seq.py
pyfread-1.5.data/scripts/esst.txt
pyfread-1.5.data/scripts/fread_db_add
pyfread-1.5.data/scripts/fread_db_optimise
pyfread-1.5.data/scripts/multifread
pyfread-1.5.data/scripts/multifread.orig
pyfread-1.5.data/scripts/pyfread
pyfread-1.5.dist-info/LICENCE
pyfread-1.5.dist-info/METADATA
pyfread-1.5.dist-info/WHEEL
pyfread-1.5.dist-info/top_level.txt
pyfread-1.5.dist-info/RECORD
