Metadata-Version: 2.1
Name: pyfread
Version: 1.5
Summary: FREAD: fragment-based loop modelling method
Home-page: http://opig.stats.ox.ac.uk/webapps/newsabdab/sabpred/fread/
Author: Sebastian Kelm
Author-email: kelm@stats.ox.ac.uk
License: UNKNOWN
Platform: UNKNOWN
License-File: LICENCE
